setup.py
micropython_os.egg-info/PKG-INFO
micropython_os.egg-info/SOURCES.txt
micropython_os.egg-info/dependency_links.txt
micropython_os.egg-info/requires.txt
micropython_os.egg-info/top_level.txt
os/__init__.py